youtube_sm_parser/__init__.py
youtube_sm_parser/__main__.py
youtube_sm_parser/youtube_sm_parser.py
youtube_sm_parser-0.1.5.dist-info/AUTHORS.rst
youtube_sm_parser-0.1.5.dist-info/LICENSE
youtube_sm_parser-0.1.5.dist-info/METADATA
youtube_sm_parser-0.1.5.dist-info/WHEEL
youtube_sm_parser-0.1.5.dist-info/entry_points.txt
youtube_sm_parser-0.1.5.dist-info/top_level.txt
youtube_sm_parser-0.1.5.dist-info/RECORD
