Metadata-Version: 2.1
Name: youtube-sm-parser
Version: 0.1.5
Summary: Output youtube subscriptions using subscription_manager file
Home-page: https://github.com/shanedabes/youtube_sm_parser
Author: Shane Donohoe
Author-email: shane@donohoe.cc
License: Apache Software License 2.0
Keywords: youtube_sm_parser
Platform: UNKNOWN
Classifier: Intended Audience :: Developers
Classifier: License :: OSI Approved :: Apache Software License
Classifier: Natural Language :: English
Classifier: Programming Language :: Python :: 3
Classifier: Programming Language :: Python :: 3.6
Classifier: Programming Language :: Python :: 3.7
Requires-Dist: requests-futures (==1.0.0)
Requires-Dist: xmltodict (==0.12.0)
Requires-Dist: PyYAML (==5.1)
